meshless/__init__.py
meshless/constants.py
meshless/interpolate.py
meshless/logger.py
meshless/utils.py
meshless/version.py
meshless/dev/__init__.py
meshless/dev/sympytools.py
meshless/dev/tests/test_sympytools.py
meshless/espim/__init__.py
meshless/espim/classes.py
meshless/espim/plate2d_add_k0s.py
meshless/espim/plate2d_add_k0s_cell_based.py
meshless/espim/plate2d_add_k0s_cell_based_no_smoothing.py
meshless/espim/plate2d_add_k0s_edge_based.py
meshless/espim/plate2d_calc_k0.py
meshless/espim/plate2d_calc_kG.py
meshless/espim/read_mesh.py
meshless/espim/tests/nastran_plate_16_nodes.dat
meshless/espim/tests/nastran_plate_16_nodes.result.txt
meshless/espim/tests/test_calc_linear_buckling.py
meshless/espim/tests/test_calc_linear_static.py
meshless/espim/tests/test_plate_from_zero.py
meshless/espim/tests/test_read_delaunay.py
meshless/espim/tests/test_read_mesh.py
meshless/tests/test_interpolate.py
meshless-0.1.28.data/data/LICENSE
meshless-0.1.28.data/data/README.md
meshless-0.1.28.data/data/version.py
meshless-0.1.28.dist-info/METADATA
meshless-0.1.28.dist-info/RECORD
meshless-0.1.28.dist-info/WHEEL
meshless-0.1.28.dist-info/top_level.txt
